[
    {
        "start": 1730140200,
        "end": 1730143800,
        "bounce": {
            "isBounced": false,
            "pathname": "/frontend/index.html"
        },
        "device": "Desktop",
        "browser": "Edge",
        "location": {
            "latitude": 30.9708585,
            "longitude": -86.221279
        },
        "uniqueId": "ca9d1f5f-925b-4a59-b362-4703a75ad77c",
        "pathname": "/frontend/index.html",
        "language": "gd",
        "referrer": "",
        "events": {
            "loadCount": 7,
            "visibilitychangeCount": 6,
            "resizeCount": 3,
            "focusCount": 5,
            "clickCount": 0,
            "blurCount": 4
        },
        "pageLoadTime": {
            "loadStart": 1730140200000,
            "loadEnd": 1730140200641
        },
        "productId": "TRK-Ob2CJVFgaau7",
        "pathCounts": {
            "/cart": 4,
            "/login": 6,
            "/home/dashboard": 10
        }
    },
    {
        "start": 1730140200,
        "end": 1730142720,
        "bounce": {
            "isBounced": true,
            "pathname": "/frontend/index.html"
        },
        "device": "Laptop",
        "browser": "Safari",
        "location": {
            "latitude": -43.921735,
            "longitude": -85.932315
        },
        "uniqueId": "14ec54a1-24e9-462b-9378-3e9d812cba5a",
        "pathname": "/home",
        "language": "gl",
        "referrer": "",
        "events": {
            "loadCount": 5,
            "visibilitychangeCount": 6,
            "resizeCount": 2,
            "focusCount": 2,
            "clickCount": 7,
            "blurCount": 10
        },
        "pageLoadTime": {
            "loadStart": 1730140200000,
            "loadEnd": 1730140200998
        },
        "productId": "TRK-Ob2CJVFgaau7",
        "pathCounts": {
            "/profile": 10,
            "/cart": 9,
            "/checkout": 6,
            "/settings": 7
        }
    },
    {
        "start": 1730140200,
        "end": 1730143740,
        "bounce": {
            "isBounced": false,
            "pathname": "/frontend/index.html"
        },
        "device": "Desktop",
        "browser": "Chrome",
        "location": {
            "latitude": -13.334106,
            "longitude": -49.554325
        },
        "uniqueId": "aa76de66-83a4-4c21-92f5-cfe20525387a",
        "pathname": "/home",
        "language": "mt",
        "referrer": "http://www.camacho.com/",
        "events": {
            "loadCount": 2,
            "visibilitychangeCount": 8,
            "resizeCount": 4,
            "focusCount": 8,
            "clickCount": 5,
            "blurCount": 4
        },
        "pageLoadTime": {
            "loadStart": 1730140200000,
            "loadEnd": 1730140200697
        },
        "productId": "TRK-Ob2CJVFgaau7",
        "pathCounts": {
            "/home/dashboard": 4,
            "/profile": 8,
            "/home/create": 4,
            "/settings": 7
        }
    },
    {
        "start": 1730140200,
        "end": 1730142240,
        "bounce": {
            "isBounced": true,
            "pathname": "/frontend/index.html"
        },
        "device": "Laptop",
        "browser": "Safari",
        "location": {
            "latitude": 32.3165275,
            "longitude": -179.494286
        },
        "uniqueId": "4f113d91-1e3e-46f7-a9ca-95f02de96297",
        "pathname": "/home",
        "language": "uz",
        "referrer": "https://www.gardner.org/",
        "events": {
            "loadCount": 5,
            "visibilitychangeCount": 1,
            "resizeCount": 1,
            "focusCount": 3,
            "clickCount": 5,
            "blurCount": 8
        },
        "pageLoadTime": {
            "loadStart": 1730140200000,
            "loadEnd": 1730140200354
        },
        "productId": "TRK-TlxlcwGkl19t",
        "pathCounts": {
            "/checkout": 3,
            "/home/dashboard": 5,
            "/login": 5,
            "/profile": 9
        }
    },
    {
        "start": 1730140200,
        "end": 1730141460,
        "bounce": {
            "isBounced": true,
            "pathname": "/frontend/index.html"
        },
        "device": "Desktop",
        "browser": "Chrome",
        "location": {
            "latitude": 36.313529,
            "longitude": -2.337167
        },
        "uniqueId": "111907fd-95b7-4729-a2af-e51ad656e288",
        "pathname": "/settings",
        "language": "ak",
        "referrer": "",
        "events": {
            "loadCount": 1,
            "visibilitychangeCount": 4,
            "resizeCount": 5,
            "focusCount": 3,
            "clickCount": 8,
            "blurCount": 9
        },
        "pageLoadTime": {
            "loadStart": 1730140200000,
            "loadEnd": 1730140200268
        },
        "productId": "TRK-Ob2CJVFgaau7",
        "pathCounts": {
            "/checkout": 4,
            "/profile": 1,
            "/cart": 1,
            "/home/create": 4
        }
    },
    {
        "start": 1730140200,
        "end": 1730143020,
        "bounce": {
            "isBounced": true,
            "pathname": "/frontend/index.html"
        },
        "device": "Mobile",
        "browser": "Safari",
        "location": {
            "latitude": -14.9808425,
            "longitude": 66.837637
        },
        "uniqueId": "9ce1bf0b-8366-40e1-b77c-9493a981c91b",
        "pathname": "/profile",
        "language": "si",
        "referrer": "",
        "events": {
            "loadCount": 6,
            "visibilitychangeCount": 5,
            "resizeCount": 4,
            "focusCount": 5,
            "clickCount": 4,
            "blurCount": 10
        },
        "pageLoadTime": {
            "loadStart": 1730140200000,
            "loadEnd": 1730140200068
        },
        "productId": "TRK-Ob2CJVFgaau7",
        "pathCounts": {
            "/checkout": 2,
            "/home/create": 3,
            "/home": 2
        }
    },
    {
        "start": 1730140200,
        "end": 1730142660,
        "bounce": {
            "isBounced": false,
            "pathname": "/frontend/index.html"
        },
        "device": "Mobile",
        "browser": "Chrome",
        "location": {
            "latitude": 73.3790005,
            "longitude": 82.745343
        },
        "uniqueId": "9b47b488-09f3-4d00-a56c-8c970bdfab8e",
        "pathname": "/home",
        "language": "raj",
        "referrer": "",
        "events": {
            "loadCount": 0,
            "visibilitychangeCount": 6,
            "resizeCount": 4,
            "focusCount": 8,
            "clickCount": 1,
            "blurCount": 6
        },
        "pageLoadTime": {
            "loadStart": 1730140200000,
            "loadEnd": 1730140200699
        },
        "productId": "TRK-Ob2CJVFgaau7",
        "pathCounts": {
            "/profile": 2,
            "/home": 6,
            "/home/dashboard": 9,
            "/home/create": 3
        }
    }
]